{
    "os": "Linux-6.5.0-18-generic-x86_64-with-glibc2.35",
    "python": "3.11.5",
    "heartbeatAt": "2024-02-21T13:51:54.653008",
    "startedAt": "2024-02-21T13:51:53.628052",
    "docker": null,
    "cuda": null,
    "args": [
        "--data_dir=./domainbed/data/MNIST/",
        "--algorithm",
        "IGA",
        "--dataset",
        "ColoredMNIST",
        "--test_env",
        "2",
        "--wandb"
    ],
    "state": "running",
    "program": "-m domainbed.scripts.train",
    "codePathLocal": null,
    "git": {
        "remote": "https://github.com/khanhkhanhlele/DomainBed",
        "commit": "c60753c8903ef5f6aae39a83988ef93eab190f58"
    },
    "email": "mduongbkhn@gmail.com",
    "root": "/home/duong/Documents/git/DomainGeneralization/KhanhLe/DomainBed",
    "host": "sky",
    "username": "duong",
    "executable": "/home/duong/Documents/git/.env/bin/python3",
    "cpu_count": 24,
    "cpu_count_logical": 32,
    "cpu_freq": {
        "current": 1747.9035625,
        "min": 800.0,
        "max": 4575.0
    },
    "cpu_freq_per_core": [
        {
            "current": 3714.596,
            "min": 800.0,
            "max": 5200.0
        },
        {
            "current": 800.0,
            "min": 800.0,
            "max": 5200.0
        },
        {
            "current": 5200.0,
            "min": 800.0,
            "max": 5200.0
        },
        {
            "current": 1377.333,
            "min": 800.0,
            "max": 5200.0
        },
        {
            "current": 5099.037,
            "min": 800.0,
            "max": 5200.0
        },
        {
            "current": 1013.266,
            "min": 800.0,
            "max": 5200.0
        },
        {
            "current": 4658.162,
            "min": 800.0,
            "max": 5200.0
        },
        {
            "current": 800.0,
            "min": 800.0,
            "max": 5200.0
        },
        {
            "current": 944.624,
            "min": 800.0,
            "max": 5400.0
        },
        {
            "current": 3540.963,
            "min": 800.0,
            "max": 5400.0
        },
        {
            "current": 3124.552,
            "min": 800.0,
            "max": 5400.0
        },
        {
            "current": 1546.562,
            "min": 800.0,
            "max": 5400.0
        },
        {
            "current": 4568.371,
            "min": 800.0,
            "max": 5200.0
        },
        {
            "current": 800.0,
            "min": 800.0,
            "max": 5200.0
        },
        {
            "current": 3737.791,
            "min": 800.0,
            "max": 5200.0
        },
        {
            "current": 887.441,
            "min": 800.0,
            "max": 5200.0
        },
        {
            "current": 800.0,
            "min": 800.0,
            "max": 3900.0
        },
        {
            "current": 800.0,
            "min": 800.0,
            "max": 3900.0
        },
        {
            "current": 800.0,
            "min": 800.0,
            "max": 3900.0
        },
        {
            "current": 800.0,
            "min": 800.0,
            "max": 3900.0
        },
        {
            "current": 800.0,
            "min": 800.0,
            "max": 3900.0
        },
        {
            "current": 2090.137,
            "min": 800.0,
            "max": 3900.0
        },
        {
            "current": 830.079,
            "min": 800.0,
            "max": 3900.0
        },
        {
            "current": 800.0,
            "min": 800.0,
            "max": 3900.0
        },
        {
            "current": 800.0,
            "min": 800.0,
            "max": 3900.0
        },
        {
            "current": 800.0,
            "min": 800.0,
            "max": 3900.0
        },
        {
            "current": 800.0,
            "min": 800.0,
            "max": 3900.0
        },
        {
            "current": 800.0,
            "min": 800.0,
            "max": 3900.0
        },
        {
            "current": 800.0,
            "min": 800.0,
            "max": 3900.0
        },
        {
            "current": 800.0,
            "min": 800.0,
            "max": 3900.0
        },
        {
            "current": 800.0,
            "min": 800.0,
            "max": 3900.0
        },
        {
            "current": 800.0,
            "min": 800.0,
            "max": 3900.0
        }
    ],
    "disk": {
        "/": {
            "total": 937.3305015563965,
            "used": 256.90971755981445
        }
    },
    "gpu": "NVIDIA GeForce RTX 4070 Laptop GPU",
    "gpu_count": 1,
    "gpu_devices": [
        {
            "name": "NVIDIA GeForce RTX 4070 Laptop GPU",
            "memory_total": 8585740288
        }
    ],
    "memory": {
        "total": 15.34946060180664
    }
}
